MANIFEST.in
README.md
setup.py
sparse_som/__init__.py
sparse_som/classifier.py
sparse_som/som.cpp
sparse_som/som.pyx
sparse_som.egg-info/PKG-INFO
sparse_som.egg-info/SOURCES.txt
sparse_som.egg-info/dependency_links.txt
sparse_som.egg-info/requires.txt
sparse_som.egg-info/top_level.txt
sparse_som/lib/bsom.cpp
sparse_som/lib/data.cpp
sparse_som/lib/data.h
sparse_som/lib/som.cpp
sparse_som/lib/som.h