Metadata-Version: 1.1
Name: sparse-som
Version: 0.6.1
Summary: Self-Organizing Maps for sparse inputs in python
Home-page: https://github.com/yoch/sparse-som
Author: J. Melka
Author-email: UNKNOWN
License: GPL3
Platform: UNKNOWN
Classifier: Development Status :: 4 - Beta
Classifier: Intended Audience :: Science/Research
Classifier: License :: OSI Approved :: GNU General Public License v3 (GPLv3)
Classifier: Operating System :: POSIX
Classifier: Operating System :: Microsoft
Classifier: Programming Language :: C++
Classifier: Programming Language :: Python :: 3
Classifier: Topic :: Scientific/Engineering :: Information Analysis
Classifier: Topic :: Scientific/Engineering :: Visualization
